<?xml version="1.0" encoding="utf-8" ?>
<dwsync>
<file name="abstract.phtml" server="saibottechnologies.com/public_html/babynaturals/" local="129497364000000000" remote="129497364000000000" />
<file name="comment.phtml" server="saibottechnologies.com/public_html/babynaturals/" local="129497364000000000" remote="129497364000000000" />
<file name="data.phtml" server="saibottechnologies.com/public_html/babynaturals/" local="129497364000000000" remote="129497364000000000" />
<file name="form.phtml" server="saibottechnologies.com/public_html/babynaturals/" local="129497364000000000" remote="129497364000000000" />
<file name="giftmessage.phtml" server="saibottechnologies.com/public_html/babynaturals/" local="129497364000000000" remote="129497364000000000" />
<file name="items.phtml" server="saibottechnologies.com/public_html/babynaturals/" local="129497364000000000" remote="129497364000000000" />
<file name="js.phtml" server="saibottechnologies.com/public_html/babynaturals/" local="129573396000000000" remote="129573396000000000" />
<file name="sidebar.phtml" server="saibottechnologies.com/public_html/babynaturals/" local="129497364000000000" remote="129497364000000000" />
<file name="totals.phtml" server="saibottechnologies.com/public_html/babynaturals/" local="129497364000000000" remote="129497364000000000" />
</dwsync>