<?xml version="1.0" encoding="utf-8" ?>
<dwsync>
<file name="catalog.xml" server="saibottechnologies.com/public_html/babynaturals/" local="129996771000000000" remote="129996771000000000" />
<file name="catalogsearch.xml" server="saibottechnologies.com/public_html/babynaturals/" local="129664116000000000" remote="129664116000000000" />
<file name="checkout.xml" server="saibottechnologies.com/public_html/babynaturals/" local="129996746400000000" remote="129996746400000000" />
<file name="customer.xml" server="saibottechnologies.com/public_html/babynaturals/" local="129996751200000000" remote="129996751200000000" />
<file name="local.xml" server="saibottechnologies.com/public_html/babynaturals/" local="129925019400000000" remote="129925019400000000" />
<file name="newsletter.xml" server="saibottechnologies.com/public_html/babynaturals/" local="129664116000000000" remote="129664116000000000" />
<file name="page.xml" server="saibottechnologies.com/public_html/babynaturals/" local="129945612000000000" remote="129945612000000000" />
<file name="persistent.xml" server="saibottechnologies.com/public_html/babynaturals/" local="129996750000000000" remote="129996750000000000" />
<file name="sendfriend.xml" server="saibottechnologies.com/public_html/babynaturals/" local="129664116000000000" remote="129664116000000000" />
</dwsync>